{"types":["real_estate_agency","point_of_interest","establishment"],"rating":5,"internationalPhoneNumber":"+1 405-334-6407","iconMaskBaseUri":"https://maps.gstatic.com/mapfiles/place_api/icons/v2/generic_pinlet","googleMapsUri":"https://maps.google.com/?cid=5282086630969803521","nationalPhoneNumber":"(405) 334-6407","primaryTypeDisplayName":{"languageCode":"en-US","text":"Real Estate Agency"},"name":"places/ChIJBZR0tuBYwokRAYPLH869TUk","location":{"latitude":40.7566249,"longitude":-73.9608234},"iconBackgroundColor":"#7B9EB0","addressComponents":[{"types":["street_number"],"languageCode":"en-US","longText":"611","shortText":"611"},{"types":["route"],"languageCode":"en","longText":"East 56th Street","shortText":"E 56th St"},{"types":["sublocality_level_1","sublocality","political"],"languageCode":"en","longText":"Manhattan","shortText":"Manhattan"},{"types":["locality","political"],"languageCode":"en","longText":"New York","shortText":"New York"},{"types":["administrative_area_level_2","political"],"languageCode":"en","longText":"New York County","shortText":"New York County"},{"types":["administrative_area_level_1","political"],"languageCode":"en","longText":"New York","shortText":"NY"},{"types":["country","political"],"languageCode":"en","longText":"United States","shortText":"US"},{"types":["postal_code"],"languageCode":"en-US","longText":"10022","shortText":"10022"}],"id":"ChIJBZR0tuBYwokRAYPLH869TUk","utcOffsetMinutes":-300,"displayName":{"languageCode":"en","text":"Lane Homes"},"primaryType":"real_estate_agency","formattedAddress":"611 E 56th St, New York, NY 10022, USA","plusCode":{"globalCode":"87G8Q24Q+JM","compoundCode":"Q24Q+JM New York, NY, USA"},"adrFormatAddress":"<span class=\"street-address\">611 E 56th St</span>, <span class=\"locality\">New York</span>, <span class=\"region\">NY</span> <span class=\"postal-code\">10022</span>, <span class=\"country-name\">USA</span>","userRatingCount":1,"reviews":[{"name":"places/ChIJBZR0tuBYwokRAYPLH869TUk/reviews/ChZDSUhNMG9nS0VJQ0FnSUNhdkwzUEx3EAE","rating":5,"authorAttribution":{"photoUri":"https://lh3.googleusercontent.com/a/ACg8ocKw4eKPfV69gMqSs_jG_GJaTaCoxs26oQy6RGE69cao=s128-c0x00000000-cc-rp-mo","uri":"https://www.google.com/maps/contrib/116370473528467292770/reviews","displayName":"Adam Chudy"},"relativePublishTimeDescription":"2 years ago","publishTime":"2021-07-26T03:07:37Z"}],"viewport":{"high":{"latitude":40.7579453802915,"longitude":-73.9594946697085},"low":{"latitude":40.7552474197085,"longitude":-73.96219263029151}},"businessStatus":"OPERATIONAL","shortFormattedAddress":"611 E 56th St, New York"}