{"types":["park","premise","point_of_interest","establishment"],"iconMaskBaseUri":"https://maps.gstatic.com/mapfiles/place_api/icons/v2/tree_pinlet","googleMapsUri":"https://maps.google.com/?cid=10317010113481712781","primaryTypeDisplayName":{"languageCode":"en-US","text":"Park"},"name":"places/ChIJLw7H4V1YwokRjaQwTgliLY8","location":{"latitude":40.774634,"longitude":-73.98906339999999},"iconBackgroundColor":"#4DB546","addressComponents":[{"types":["route"],"languageCode":"en","longText":"West 63rd Street","shortText":"W 63rd St."},{"types":["sublocality_level_1","sublocality","political"],"languageCode":"en","longText":"Manhattan","shortText":"Manhattan"},{"types":["locality","political"],"languageCode":"en","longText":"New York","shortText":"New York"},{"types":["administrative_area_level_2","political"],"languageCode":"en","longText":"New York County","shortText":"New York County"},{"types":["administrative_area_level_1","political"],"languageCode":"en","longText":"New York","shortText":"NY"},{"types":["country","political"],"languageCode":"en","longText":"United States","shortText":"US"},{"types":["postal_code"],"languageCode":"en-US","longText":"10023","shortText":"10023"}],"id":"ChIJLw7H4V1YwokRjaQwTgliLY8","utcOffsetMinutes":-300,"displayName":{"languageCode":"en","text":"West 63rd Street"},"primaryType":"park","formattedAddress":"W 63rd St., New York, NY 10023, USA","adrFormatAddress":"<span class=\"street-address\">W 63rd St.</span>, <span class=\"locality\">New York</span>, <span class=\"region\">NY</span> <span class=\"postal-code\">10023</span>, <span class=\"country-name\">USA</span>","viewport":{"high":{"latitude":40.77599869185656,"longitude":-73.9875631197074},"low":{"latitude":40.773300731273565,"longitude":-73.99026108029041}},"shortFormattedAddress":"W 63rd St., New York"}