{"websiteUri":"http://www.learnjapaneseny.com/","types":["school","point_of_interest","establishment"],"internationalPhoneNumber":"+1 212-697-8374","iconMaskBaseUri":"https://maps.gstatic.com/mapfiles/place_api/icons/v2/school_pinlet","googleMapsUri":"https://maps.google.com/?cid=2343371193100379182","nationalPhoneNumber":"(212) 697-8374","primaryTypeDisplayName":{"languageCode":"en-US","text":"School"},"name":"places/ChIJW_96_-NYwokRLqShNa9ThSA","location":{"latitude":40.757721599999996,"longitude":-73.96600459999999},"iconBackgroundColor":"#7B9EB0","addressComponents":[{"types":["street_number"],"languageCode":"en-US","longText":"300-398","shortText":"300-398"},{"types":["route"],"languageCode":"en","longText":"East 55th Street","shortText":"E 55th St"},{"types":["sublocality_level_1","sublocality","political"],"languageCode":"en","longText":"Manhattan","shortText":"Manhattan"},{"types":["locality","political"],"languageCode":"en","longText":"New York","shortText":"New York"},{"types":["administrative_area_level_2","political"],"languageCode":"en","longText":"New York County","shortText":"New York County"},{"types":["administrative_area_level_1","political"],"languageCode":"en","longText":"New York","shortText":"NY"},{"types":["country","political"],"languageCode":"en","longText":"United States","shortText":"US"},{"types":["postal_code"],"languageCode":"en-US","longText":"10022","shortText":"10022"}],"id":"ChIJW_96_-NYwokRLqShNa9ThSA","utcOffsetMinutes":-300,"displayName":{"languageCode":"en","text":"Amity Language Institute LEARN Japanese"},"primaryType":"school","formattedAddress":"300-398 E 55th St, New York, NY 10022, USA","regularOpeningHours":{"openNow":true,"periods":[{"open":{"day":0,"hour":9,"minute":0},"close":{"day":0,"hour":17,"minute":0}},{"open":{"day":1,"hour":9,"minute":0},"close":{"day":1,"hour":17,"minute":0}},{"open":{"day":2,"hour":9,"minute":0},"close":{"day":2,"hour":17,"minute":0}},{"open":{"day":3,"hour":9,"minute":0},"close":{"day":3,"hour":17,"minute":0}},{"open":{"day":4,"hour":9,"minute":0},"close":{"day":4,"hour":17,"minute":0}},{"open":{"day":5,"hour":9,"minute":0},"close":{"day":5,"hour":17,"minute":0}},{"open":{"day":6,"hour":9,"minute":0},"close":{"day":6,"hour":17,"minute":0}}],"weekdayDescriptions":["Monday: 9:00 AM – 5:00 PM","Tuesday: 9:00 AM – 5:00 PM","Wednesday: 9:00 AM – 5:00 PM","Thursday: 9:00 AM – 5:00 PM","Friday: 9:00 AM – 5:00 PM","Saturday: 9:00 AM – 5:00 PM","Sunday: 9:00 AM – 5:00 PM"]},"plusCode":{"globalCode":"87G8Q25M+3H","compoundCode":"Q25M+3H New York, NY, USA"},"adrFormatAddress":"<span class=\"street-address\">300-398 E 55th St</span>, <span class=\"locality\">New York</span>, <span class=\"region\">NY</span> <span class=\"postal-code\">10022</span>, <span class=\"country-name\">USA</span>","viewport":{"high":{"latitude":40.759146280291496,"longitude":-73.96459936970848},"low":{"latitude":40.7564483197085,"longitude":-73.9672973302915}},"businessStatus":"OPERATIONAL","currentOpeningHours":{"openNow":true,"periods":[{"open":{"day":0,"hour":9,"date":{"day":18,"month":2,"year":2024},"minute":0},"close":{"day":0,"hour":17,"date":{"day":18,"month":2,"year":2024},"minute":0}},{"open":{"day":1,"hour":9,"date":{"day":19,"month":2,"year":2024},"minute":0},"close":{"day":1,"hour":17,"date":{"day":19,"month":2,"year":2024},"minute":0}},{"open":{"day":2,"hour":9,"date":{"day":20,"month":2,"year":2024},"minute":0},"close":{"day":2,"hour":17,"date":{"day":20,"month":2,"year":2024},"minute":0}},{"open":{"day":3,"hour":9,"date":{"day":21,"month":2,"year":2024},"minute":0},"close":{"day":3,"hour":17,"date":{"day":21,"month":2,"year":2024},"minute":0}},{"open":{"day":4,"hour":9,"date":{"day":22,"month":2,"year":2024},"minute":0},"close":{"day":4,"hour":17,"date":{"day":22,"month":2,"year":2024},"minute":0}},{"open":{"day":5,"hour":9,"date":{"day":23,"month":2,"year":2024},"minute":0},"close":{"day":5,"hour":17,"date":{"day":23,"month":2,"year":2024},"minute":0}},{"open":{"day":6,"hour":9,"date":{"day":17,"month":2,"year":2024},"minute":0},"close":{"day":6,"hour":17,"date":{"day":17,"month":2,"year":2024},"minute":0}}],"weekdayDescriptions":["Monday: 9:00 AM – 5:00 PM","Tuesday: 9:00 AM – 5:00 PM","Wednesday: 9:00 AM – 5:00 PM","Thursday: 9:00 AM – 5:00 PM","Friday: 9:00 AM – 5:00 PM","Saturday: 9:00 AM – 5:00 PM","Sunday: 9:00 AM – 5:00 PM"]},"shortFormattedAddress":"300-398 E 55th St, New York"}