{"websiteUri":"https://www.taysteebldg.com/","types":["point_of_interest","establishment"],"rating":5,"iconMaskBaseUri":"https://maps.gstatic.com/mapfiles/place_api/icons/v2/generic_pinlet","accessibilityOptions":{"wheelchairAccessibleEntrance":true},"googleMapsUri":"https://maps.google.com/?cid=11717639244168127270","name":"places/ChIJQ5KUSKT3wokRJmPRUs9qnaI","location":{"latitude":40.813109,"longitude":-73.9549756},"iconBackgroundColor":"#7B9EB0","addressComponents":[{"types":["street_number"],"languageCode":"en-US","longText":"450","shortText":"450"},{"types":["route"],"languageCode":"en","longText":"West 126th Street","shortText":"W 126th St"},{"types":["sublocality_level_1","sublocality","political"],"languageCode":"en","longText":"Manhattan","shortText":"Manhattan"},{"types":["locality","political"],"languageCode":"en","longText":"New York","shortText":"New York"},{"types":["administrative_area_level_2","political"],"languageCode":"en","longText":"New York County","shortText":"New York County"},{"types":["administrative_area_level_1","political"],"languageCode":"en","longText":"New York","shortText":"NY"},{"types":["country","political"],"languageCode":"en","longText":"United States","shortText":"US"},{"types":["postal_code"],"languageCode":"en-US","longText":"10027","shortText":"10027"}],"id":"ChIJQ5KUSKT3wokRJmPRUs9qnaI","utcOffsetMinutes":-300,"displayName":{"languageCode":"en","text":"Taystee Life Science Building"},"formattedAddress":"450 W 126th St, New York, NY 10027, USA","plusCode":{"globalCode":"87G8R27W+62","compoundCode":"R27W+62 New York, NY, USA"},"adrFormatAddress":"<span class=\"street-address\">450 W 126th St</span>, <span class=\"locality\">New York</span>, <span class=\"region\">NY</span> <span class=\"postal-code\">10027</span>, <span class=\"country-name\">USA</span>","userRatingCount":2,"reviews":[{"name":"places/ChIJQ5KUSKT3wokRJmPRUs9qnaI/reviews/ChdDSUhNMG9nS0VJQ0FnSUNSam9YRXd3RRAB","rating":5,"authorAttribution":{"photoUri":"https://lh3.googleusercontent.com/a/ACg8ocJU4ePWaCdfUrsvL-_mBTOfBZ1J8cYJk-9hZ0qtlrLx=s128-c0x00000000-cc-rp-mo","uri":"https://www.google.com/maps/contrib/108407386781697338539/reviews","displayName":"igor stern"},"relativePublishTimeDescription":"10 months ago","publishTime":"2023-04-01T22:46:26Z"},{"name":"places/ChIJQ5KUSKT3wokRJmPRUs9qnaI/reviews/ChdDSUhNMG9nS0VJQ0FnSURleHVMT2x3RRAB","rating":5,"authorAttribution":{"photoUri":"https://lh3.googleusercontent.com/a/ACg8ocI52M8GTUN-crwPvT_Y905bjYkNk5IK4MuyV2pdKszD=s128-c0x00000000-cc-rp-mo-ba4","uri":"https://www.google.com/maps/contrib/112766695689659467724/reviews","displayName":"Aleks Kaliuzhnyi"},"relativePublishTimeDescription":"a year ago","publishTime":"2022-10-08T22:47:11Z"}],"viewport":{"high":{"latitude":40.8144844802915,"longitude":-73.95357356970848},"low":{"latitude":40.8117865197085,"longitude":-73.9562715302915}},"businessStatus":"OPERATIONAL","shortFormattedAddress":"450 W 126th St, New York"}