{"types":["synagogue","place_of_worship","point_of_interest","establishment"],"internationalPhoneNumber":"+1 212-923-3319","iconMaskBaseUri":"https://maps.gstatic.com/mapfiles/place_api/icons/v2/worship_jewish_pinlet","googleMapsUri":"https://maps.google.com/?cid=10576525284014421430","nationalPhoneNumber":"(212) 923-3319","primaryTypeDisplayName":{"languageCode":"en-US","text":"Synagogue"},"name":"places/ChIJue0NdR30wokRtvWdf7Vdx5I","location":{"latitude":40.854214,"longitude":-73.9345962},"iconBackgroundColor":"#7B9EB0","addressComponents":[{"types":["street_number"],"languageCode":"en-US","longText":"131","shortText":"131"},{"types":["route"],"languageCode":"en","longText":"Bennett Avenue","shortText":"Bennett Ave"},{"types":["sublocality_level_1","sublocality","political"],"languageCode":"en","longText":"Manhattan","shortText":"Manhattan"},{"types":["locality","political"],"languageCode":"en","longText":"New York","shortText":"New York"},{"types":["administrative_area_level_2","political"],"languageCode":"en","longText":"New York County","shortText":"New York County"},{"types":["administrative_area_level_1","political"],"languageCode":"en","longText":"New York","shortText":"NY"},{"types":["country","political"],"languageCode":"en","longText":"United States","shortText":"US"},{"types":["postal_code"],"languageCode":"en-US","longText":"10033","shortText":"10033"},{"types":["postal_code_suffix"],"languageCode":"en-US","longText":"2315","shortText":"2315"}],"id":"ChIJue0NdR30wokRtvWdf7Vdx5I","utcOffsetMinutes":-300,"displayName":{"languageCode":"en","text":"Krieger Joseph"},"primaryType":"synagogue","formattedAddress":"131 Bennett Ave, New York, NY 10033, USA","plusCode":{"globalCode":"87G8V338+M5","compoundCode":"V338+M5 New York, NY, USA"},"adrFormatAddress":"<span class=\"street-address\">131 Bennett Ave</span>, <span class=\"locality\">New York</span>, <span class=\"region\">NY</span> <span class=\"postal-code\">10033-2315</span>, <span class=\"country-name\">USA</span>","viewport":{"high":{"latitude":40.8555231802915,"longitude":-73.9333336697085},"low":{"latitude":40.85282521970851,"longitude":-73.93603163029151}},"businessStatus":"OPERATIONAL","shortFormattedAddress":"131 Bennett Ave, New York"}