{"websiteUri":"http://lererhippeau.com/","types":["finance","point_of_interest","establishment"],"rating":5,"internationalPhoneNumber":"+1 646-237-4837","iconMaskBaseUri":"https://maps.gstatic.com/mapfiles/place_api/icons/v2/generic_pinlet","accessibilityOptions":{"wheelchairAccessibleEntrance":true},"googleMapsUri":"https://maps.google.com/?cid=18386053487171394955","nationalPhoneNumber":"(646) 237-4837","name":"places/ChIJwz7F4Y5ZwokRi90urDtiKP8","location":{"latitude":40.7277098,"longitude":-74.00861139999999},"iconBackgroundColor":"#7B9EB0","addressComponents":[{"types":["street_number"],"languageCode":"en-US","longText":"555","shortText":"555"},{"types":["route"],"languageCode":"en","longText":"Greenwich Street","shortText":"Greenwich St"},{"types":["sublocality_level_1","sublocality","political"],"languageCode":"en","longText":"Manhattan","shortText":"Manhattan"},{"types":["locality","political"],"languageCode":"en","longText":"New York","shortText":"New York"},{"types":["administrative_area_level_2","political"],"languageCode":"en","longText":"New York County","shortText":"New York County"},{"types":["administrative_area_level_1","political"],"languageCode":"en","longText":"New York","shortText":"NY"},{"types":["country","political"],"languageCode":"en","longText":"United States","shortText":"US"},{"types":["postal_code"],"languageCode":"en-US","longText":"10014","shortText":"10014"}],"id":"ChIJwz7F4Y5ZwokRi90urDtiKP8","utcOffsetMinutes":-300,"displayName":{"languageCode":"en","text":"Lerer Hippeau"},"formattedAddress":"555 Greenwich St, New York, NY 10014, USA","plusCode":{"globalCode":"87G7PXHR+3H","compoundCode":"PXHR+3H New York, NY, USA"},"adrFormatAddress":"<span class=\"street-address\">555 Greenwich St</span>, <span class=\"locality\">New York</span>, <span class=\"region\">NY</span> <span class=\"postal-code\">10014</span>, <span class=\"country-name\">USA</span>","userRatingCount":1,"reviews":[{"name":"places/ChIJwz7F4Y5ZwokRi90urDtiKP8/reviews/ChZDSUhNMG9nS0VJQ0FnSUN1dHBERVNnEAE","rating":5,"authorAttribution":{"photoUri":"https://lh3.googleusercontent.com/a/ACg8ocJzXbOi0BeWcBTW6-IKQ16v53BfIcZURw7o5WCPvRs=s128-c0x00000000-cc-rp-mo","uri":"https://www.google.com/maps/contrib/114407172222323116707/reviews","displayName":"רון ירושלימסקי"},"originalText":{"languageCode":"en","text":"From the doordash driver ❤️ To you, awesome people, amazing workplace, thank you."},"relativePublishTimeDescription":"a year ago","text":{"languageCode":"en","text":"From the doordash driver ❤️ To you, awesome people, amazing workplace, thank you."},"publishTime":"2022-07-27T21:03:18Z"}],"viewport":{"high":{"latitude":40.729068730291495,"longitude":-74.00736786970849},"low":{"latitude":40.726370769708495,"longitude":-74.0100658302915}},"businessStatus":"OPERATIONAL","shortFormattedAddress":"Hudson Street, 555 Greenwich St, New York"}