{"types":["home_goods_store","store","point_of_interest","establishment"],"rating":3.3,"iconMaskBaseUri":"https://maps.gstatic.com/mapfiles/place_api/icons/v2/shopping_pinlet","accessibilityOptions":{"wheelchairAccessibleParking":false},"googleMapsUri":"https://maps.google.com/?cid=14033979946071496071","primaryTypeDisplayName":{"languageCode":"en-US","text":"Home Goods Store"},"name":"places/ChIJkfPG5-P3wokRhxWM3me2wsI","location":{"latitude":40.8142609,"longitude":-73.95669939999999},"iconBackgroundColor":"#4B96F3","addressComponents":[{"types":["street_number"],"languageCode":"en-US","longText":"521","shortText":"521"},{"types":["route"],"languageCode":"en","longText":"West 125th Street","shortText":"W 125th St"},{"types":["sublocality_level_1","sublocality","political"],"languageCode":"en","longText":"Manhattan","shortText":"Manhattan"},{"types":["locality","political"],"languageCode":"en","longText":"New York","shortText":"New York"},{"types":["administrative_area_level_2","political"],"languageCode":"en","longText":"New York County","shortText":"New York County"},{"types":["administrative_area_level_1","political"],"languageCode":"en","longText":"New York","shortText":"NY"},{"types":["country","political"],"languageCode":"en","longText":"United States","shortText":"US"},{"types":["postal_code"],"languageCode":"en-US","longText":"10027","shortText":"10027"}],"id":"ChIJkfPG5-P3wokRhxWM3me2wsI","utcOffsetMinutes":-300,"displayName":{"languageCode":"en","text":"125 St 99¢ Mart"},"primaryType":"home_goods_store","formattedAddress":"521 W 125th St, New York, NY 10027, USA","paymentOptions":{"acceptsCreditCards":true,"acceptsCashOnly":false,"acceptsDebitCards":true,"acceptsNfc":true},"delivery":false,"plusCode":{"globalCode":"87G8R27V+P8","compoundCode":"R27V+P8 New York, NY, USA"},"adrFormatAddress":"<span class=\"street-address\">521 W 125th St</span>, <span class=\"locality\">New York</span>, <span class=\"region\">NY</span> <span class=\"postal-code\">10027</span>, <span class=\"country-name\">USA</span>","userRatingCount":3,"reviews":[{"name":"places/ChIJkfPG5-P3wokRhxWM3me2wsI/reviews/ChZDSUhNMG9nS0VJQ0FnSUNWN3REdVZREAE","rating":5,"authorAttribution":{"photoUri":"https://lh3.googleusercontent.com/a/ACg8ocJt1mc7A1fdlwH1wUFMSx21cQ_N7l4O5QWTY2xHjca7=s128-c0x00000000-cc-rp-mo","uri":"https://www.google.com/maps/contrib/117870191186175061582/reviews","displayName":"marion fontaine"},"originalText":{"languageCode":"en","text":"Friendly people!"},"relativePublishTimeDescription":"2 months ago","text":{"languageCode":"en","text":"Friendly people!"},"publishTime":"2023-12-07T07:52:11Z"},{"name":"places/ChIJkfPG5-P3wokRhxWM3me2wsI/reviews/ChZDSUhNMG9nS0VJQ0FnSUMta2YzeU9nEAE","rating":1,"authorAttribution":{"photoUri":"https://lh3.googleusercontent.com/a/ACg8ocLrpXOyPOAaM9DyMvJ1_aAsjFioy_N60aT5ZFWkFM_0=s128-c0x00000000-cc-rp-mo","uri":"https://www.google.com/maps/contrib/106558277132671085912/reviews","displayName":"Icon Don"},"originalText":{"languageCode":"en","text":"Kind of expensive"},"relativePublishTimeDescription":"a year ago","text":{"languageCode":"en","text":"Kind of expensive"},"publishTime":"2022-11-06T11:51:45Z"},{"name":"places/ChIJkfPG5-P3wokRhxWM3me2wsI/reviews/ChdDSUhNMG9nS0VJQ0FnSUNlbmQybjNnRRAB","rating":4,"authorAttribution":{"photoUri":"https://lh3.googleusercontent.com/a/ACg8ocJxjtlMD0CN41t_GR_5geXp0drdKj6lYEagMKPp4Y0i=s128-c0x00000000-cc-rp-mo-ba2","uri":"https://www.google.com/maps/contrib/109698014618173500328/reviews","displayName":"Kevin Kimbrough"},"relativePublishTimeDescription":"a year ago","publishTime":"2022-09-21T10:53:21Z"}],"viewport":{"high":{"latitude":40.8155399802915,"longitude":-73.95545896970849},"low":{"latitude":40.8128420197085,"longitude":-73.9581569302915}},"businessStatus":"OPERATIONAL","shortFormattedAddress":"521 W 125th St, New York"}