{"websiteUri":"https://www.nyrp.org/green-spaces/garden-details/family-garden-sponsored-by-tiffany-and-co/","types":["premise","park","point_of_interest","establishment"],"iconMaskBaseUri":"https://maps.gstatic.com/mapfiles/place_api/icons/v2/tree_pinlet","googleMapsUri":"https://maps.google.com/?cid=17451693515800466383","primaryTypeDisplayName":{"languageCode":"en-US","text":"Park"},"name":"places/ChIJM1OUlv31wokRz1NGIsreMPI","location":{"latitude":40.7942495,"longitude":-73.9348144},"iconBackgroundColor":"#4DB546","addressComponents":[{"types":["street_number"],"languageCode":"en-US","longText":"431","shortText":"431"},{"types":["route"],"languageCode":"en","longText":"East 114th Street","shortText":"E 114th St"},{"types":["sublocality_level_1","sublocality","political"],"languageCode":"en","longText":"Manhattan","shortText":"Manhattan"},{"types":["locality","political"],"languageCode":"en","longText":"New York","shortText":"New York"},{"types":["administrative_area_level_2","political"],"languageCode":"en","longText":"New York County","shortText":"New York County"},{"types":["administrative_area_level_1","political"],"languageCode":"en","longText":"New York","shortText":"NY"},{"types":["country","political"],"languageCode":"en","longText":"United States","shortText":"US"},{"types":["postal_code"],"languageCode":"en-US","longText":"10029","shortText":"10029"}],"id":"ChIJM1OUlv31wokRz1NGIsreMPI","utcOffsetMinutes":-300,"displayName":{"text":"431 E 114th St"},"primaryType":"park","formattedAddress":"431 E 114th St, New York, NY 10029, USA","adrFormatAddress":"<span class=\"street-address\">431 E 114th St</span>, <span class=\"locality\">New York</span>, <span class=\"region\">NY</span> <span class=\"postal-code\">10029</span>, <span class=\"country-name\">USA</span>","viewport":{"high":{"latitude":40.795615996134664,"longitude":-73.93344108353051},"low":{"latitude":40.792918035551665,"longitude":-73.93613904411352}},"shortFormattedAddress":"431 E 114th St, New York"}