{"types":["premise","parking","point_of_interest","establishment"],"iconMaskBaseUri":"https://maps.gstatic.com/mapfiles/place_api/icons/v2/parking_pinlet","googleMapsUri":"https://maps.google.com/?cid=8085825015157556103","primaryTypeDisplayName":{"languageCode":"en-US","text":"Parking"},"name":"places/ChIJM1ukRBlawokRhwNvwAKfNnA","location":{"latitude":40.7137768,"longitude":-74.0115932},"iconBackgroundColor":"#7B9EB0","addressComponents":[{"types":["neighborhood","political"],"languageCode":"en","longText":"Financial District","shortText":"Financial District"},{"types":["sublocality_level_1","sublocality","political"],"languageCode":"en","longText":"Manhattan","shortText":"Manhattan"},{"types":["locality","political"],"languageCode":"en","longText":"New York","shortText":"New York"},{"types":["administrative_area_level_2","political"],"languageCode":"en","longText":"New York County","shortText":"New York County"},{"types":["administrative_area_level_1","political"],"languageCode":"en","longText":"New York","shortText":"NY"},{"types":["country","political"],"languageCode":"en","longText":"United States","shortText":"US"},{"types":["postal_code"],"languageCode":"en-US","longText":"10007","shortText":"10007"}],"id":"ChIJM1ukRBlawokRhwNvwAKfNnA","utcOffsetMinutes":-300,"displayName":{"languageCode":"en","text":"Financial District"},"primaryType":"parking","formattedAddress":"Financial District, New York, NY 10007, USA","adrFormatAddress":"Financial District, <span class=\"locality\">New York</span>, <span class=\"region\">NY</span> <span class=\"postal-code\">10007</span>, <span class=\"country-name\">USA</span>","viewport":{"high":{"latitude":40.71512296631603,"longitude":-74.01024048245208},"low":{"latitude":40.71242500573303,"longitude":-74.01293844303508}},"shortFormattedAddress":"New York"}