{"types":["store","point_of_interest","establishment"],"iconMaskBaseUri":"https://maps.gstatic.com/mapfiles/place_api/icons/v2/shopping_pinlet","googleMapsUri":"https://maps.google.com/?cid=4642717235724479032","primaryTypeDisplayName":{"languageCode":"en-US","text":"Store"},"name":"places/ChIJH2mH1albwokROOrwS7o-bkA","location":{"latitude":40.716400799999995,"longitude":-73.9979093},"iconBackgroundColor":"#4B96F3","addressComponents":[{"types":["subpremise"],"languageCode":"en","longText":"B","shortText":"B"},{"types":["street_number"],"languageCode":"en-US","longText":"74","shortText":"74"},{"types":["route"],"languageCode":"en","longText":"Mott Street","shortText":"Mott St"},{"types":["sublocality_level_1","sublocality","political"],"languageCode":"en","longText":"Manhattan","shortText":"Manhattan"},{"types":["locality","political"],"languageCode":"en","longText":"New York","shortText":"New York"},{"types":["administrative_area_level_2","political"],"languageCode":"en","longText":"New York County","shortText":"New York County"},{"types":["administrative_area_level_1","political"],"languageCode":"en","longText":"New York","shortText":"NY"},{"types":["country","political"],"languageCode":"en","longText":"United States","shortText":"US"},{"types":["postal_code"],"languageCode":"en-US","longText":"10013","shortText":"10013"},{"types":["postal_code_suffix"],"languageCode":"en-US","longText":"4842","shortText":"4842"}],"id":"ChIJH2mH1albwokROOrwS7o-bkA","utcOffsetMinutes":-300,"displayName":{"languageCode":"en","text":"Rainbow Pavilion Trading Inc."},"primaryType":"store","formattedAddress":"74 Mott St B, New York, NY 10013, USA","plusCode":{"globalCode":"87G8P282+HR","compoundCode":"P282+HR New York, NY, USA"},"adrFormatAddress":"<span class=\"street-address\">74 Mott St B</span>, <span class=\"locality\">New York</span>, <span class=\"region\">NY</span> <span class=\"postal-code\">10013-4842</span>, <span class=\"country-name\">USA</span>","viewport":{"high":{"latitude":40.7177677302915,"longitude":-73.99661111970849},"low":{"latitude":40.7150697697085,"longitude":-73.99930908029151}},"businessStatus":"OPERATIONAL","shortFormattedAddress":"74 Mott St B, New York"}