{"websiteUri":"https://usebounce.com/","types":["storage","store","point_of_interest","establishment"],"rating":1,"internationalPhoneNumber":"+1 347-970-7778","iconMaskBaseUri":"https://maps.gstatic.com/mapfiles/place_api/icons/v2/generic_pinlet","googleMapsUri":"https://maps.google.com/?cid=4645956995336317745","nationalPhoneNumber":"(347) 970-7778","name":"places/ChIJCeA6x7ZZwokRMSvDnEXBeUA","location":{"latitude":40.7660116,"longitude":-73.9805433},"iconBackgroundColor":"#7B9EB0","addressComponents":[{"types":["street_number"],"languageCode":"en-US","longText":"205","shortText":"205"},{"types":["route"],"languageCode":"en","longText":"West 57th Street","shortText":"W 57th St"},{"types":["sublocality_level_1","sublocality","political"],"languageCode":"en","longText":"Manhattan","shortText":"Manhattan"},{"types":["locality","political"],"languageCode":"en","longText":"New York","shortText":"New York"},{"types":["administrative_area_level_2","political"],"languageCode":"en","longText":"New York County","shortText":"New York County"},{"types":["administrative_area_level_1","political"],"languageCode":"en","longText":"New York","shortText":"NY"},{"types":["country","political"],"languageCode":"en","longText":"United States","shortText":"US"},{"types":["postal_code"],"languageCode":"en-US","longText":"10019","shortText":"10019"}],"id":"ChIJCeA6x7ZZwokRMSvDnEXBeUA","utcOffsetMinutes":-300,"displayName":{"languageCode":"en","text":"Bounce Luggage Storage (Reserve Online)"},"formattedAddress":"205 W 57th St, New York, NY 10019, USA","plusCode":{"globalCode":"87G8Q289+CQ","compoundCode":"Q289+CQ New York, NY, USA"},"adrFormatAddress":"<span class=\"street-address\">205 W 57th St</span>, <span class=\"locality\">New York</span>, <span class=\"region\">NY</span> <span class=\"postal-code\">10019</span>, <span class=\"country-name\">USA</span>","userRatingCount":1,"reviews":[{"name":"places/ChIJCeA6x7ZZwokRMSvDnEXBeUA/reviews/ChdDSUhNMG9nS0VJQ0FnSURPbThqaDJ3RRAB","rating":1,"authorAttribution":{"photoUri":"https://lh3.googleusercontent.com/a-/ALV-UjWdS4AeeX045zvUeVHtmBripk067yNH8_K6FlSHbzkT1e0=s128-c0x00000000-cc-rp-mo","uri":"https://www.google.com/maps/contrib/114924727252299438359/reviews","displayName":"Luca Tunyogi"},"originalText":{"languageCode":"en","text":"It’s not there"},"relativePublishTimeDescription":"a year ago","text":{"languageCode":"en","text":"It’s not there"},"publishTime":"2022-07-14T16:38:09Z"}],"viewport":{"high":{"latitude":40.767260180291494,"longitude":-73.9792689697085},"low":{"latitude":40.764562219708495,"longitude":-73.9819669302915}},"businessStatus":"CLOSED_TEMPORARILY","shortFormattedAddress":"205 W 57th St, New York"}