{"types":["store","point_of_interest","establishment"],"iconMaskBaseUri":"https://maps.gstatic.com/mapfiles/place_api/icons/v2/generic_pinlet","googleMapsUri":"https://maps.google.com/?cid=12407686401357560980","primaryTypeDisplayName":{"languageCode":"en-US","text":"Store"},"name":"places/ChIJTwQQcuL1wokRlLxcFQv1MKw","location":{"latitude":40.8011246,"longitude":-73.93529529999999},"iconBackgroundColor":"#13B5C7","addressComponents":[{"types":["subpremise"],"languageCode":"en","longText":"2205","shortText":"2205"},{"types":["street_number"],"languageCode":"en-US","longText":"2383","shortText":"2383"},{"types":["route"],"languageCode":"en","longText":"2nd Avenue","shortText":"2nd Ave"},{"types":["sublocality_level_1","sublocality","political"],"languageCode":"en","longText":"Manhattan","shortText":"Manhattan"},{"types":["locality","political"],"languageCode":"en","longText":"New York","shortText":"New York"},{"types":["administrative_area_level_2","political"],"languageCode":"en","longText":"New York County","shortText":"New York County"},{"types":["administrative_area_level_1","political"],"languageCode":"en","longText":"New York","shortText":"NY"},{"types":["country","political"],"languageCode":"en","longText":"United States","shortText":"US"},{"types":["postal_code"],"languageCode":"en-US","longText":"10035","shortText":"10035"}],"id":"ChIJTwQQcuL1wokRlLxcFQv1MKw","utcOffsetMinutes":-300,"displayName":{"languageCode":"en","text":"Diamond In A Rough ENTERTAINMENT, LLC"},"primaryType":"store","formattedAddress":"2383 2nd Ave #2205, New York, NY 10035, USA","plusCode":{"globalCode":"87G8R327+CV","compoundCode":"R327+CV New York, NY, USA"},"adrFormatAddress":"<span class=\"street-address\">2383 2nd Ave #2205</span>, <span class=\"locality\">New York</span>, <span class=\"region\">NY</span> <span class=\"postal-code\">10035</span>, <span class=\"country-name\">USA</span>","viewport":{"high":{"latitude":40.8024074302915,"longitude":-73.9339159697085},"low":{"latitude":40.7997094697085,"longitude":-73.9366139302915}},"businessStatus":"CLOSED_TEMPORARILY","shortFormattedAddress":"2383 2nd Ave #2205, New York"}