{"types":["dentist","point_of_interest","health","establishment"],"internationalPhoneNumber":"+1 212-861-3033","iconMaskBaseUri":"https://maps.gstatic.com/mapfiles/place_api/icons/v2/generic_pinlet","googleMapsUri":"https://maps.google.com/?cid=12496996368795609336","nationalPhoneNumber":"(212) 861-3033","primaryTypeDisplayName":{"languageCode":"en-US","text":"Dentist"},"name":"places/ChIJI17bmJVYwokR-KhoSfw_bq0","location":{"latitude":40.7745604,"longitude":-73.9609134},"iconBackgroundColor":"#7B9EB0","addressComponents":[{"types":["subpremise"],"languageCode":"en","longText":"# 1E","shortText":"# 1E"},{"types":["street_number"],"languageCode":"en-US","longText":"875","shortText":"875"},{"types":["route"],"languageCode":"en","longText":"Park Avenue","shortText":"Park Ave"},{"types":["sublocality_level_1","sublocality","political"],"languageCode":"en","longText":"Manhattan","shortText":"Manhattan"},{"types":["locality","political"],"languageCode":"en","longText":"New York","shortText":"New York"},{"types":["administrative_area_level_2","political"],"languageCode":"en","longText":"New York County","shortText":"New York County"},{"types":["administrative_area_level_1","political"],"languageCode":"en","longText":"New York","shortText":"NY"},{"types":["country","political"],"languageCode":"en","longText":"United States","shortText":"US"},{"types":["postal_code"],"languageCode":"en-US","longText":"10075","shortText":"10075"},{"types":["postal_code_suffix"],"languageCode":"en-US","longText":"0382","shortText":"0382"}],"id":"ChIJI17bmJVYwokR-KhoSfw_bq0","utcOffsetMinutes":-300,"displayName":{"languageCode":"en","text":"Garrizo Meggie"},"primaryType":"dentist","formattedAddress":"875 Park Ave # 1E, New York, NY 10075, USA","restroom":true,"plusCode":{"globalCode":"87G8Q2FQ+RJ","compoundCode":"Q2FQ+RJ New York, NY, USA"},"adrFormatAddress":"<span class=\"street-address\">875 Park Ave # 1E</span>, <span class=\"locality\">New York</span>, <span class=\"region\">NY</span> <span class=\"postal-code\">10075-0382</span>, <span class=\"country-name\">USA</span>","viewport":{"high":{"latitude":40.7759537802915,"longitude":-73.95967141970849},"low":{"latitude":40.7732558197085,"longitude":-73.9623693802915}},"businessStatus":"OPERATIONAL","shortFormattedAddress":"875 Park Ave # 1E, New York"}