{"websiteUri":"https://www.att.com/internet/","priceLevel":"PRICE_LEVEL_MODERATE","types":["point_of_interest","establishment"],"rating":5,"iconMaskBaseUri":"https://maps.gstatic.com/mapfiles/place_api/icons/v2/generic_pinlet","googleMapsUri":"https://maps.google.com/?cid=12917890876921023662","name":"places/ChIJSx9YEKJZwokRrgwjhk-RRbM","location":{"latitude":40.7370595,"longitude":-73.9897507},"iconBackgroundColor":"#7B9EB0","addressComponents":[{"types":["street_number"],"languageCode":"en-US","longText":"31","shortText":"31"},{"types":["route"],"languageCode":"en","longText":"East 17th Street","shortText":"E 17th St"},{"types":["sublocality_level_1","sublocality","political"],"languageCode":"en","longText":"Manhattan","shortText":"Manhattan"},{"types":["locality","political"],"languageCode":"en","longText":"New York","shortText":"New York"},{"types":["administrative_area_level_2","political"],"languageCode":"en","longText":"New York County","shortText":"New York County"},{"types":["administrative_area_level_1","political"],"languageCode":"en","longText":"New York","shortText":"NY"},{"types":["country","political"],"languageCode":"en","longText":"United States","shortText":"US"},{"types":["postal_code"],"languageCode":"en-US","longText":"10003","shortText":"10003"}],"id":"ChIJSx9YEKJZwokRrgwjhk-RRbM","utcOffsetMinutes":-300,"displayName":{"languageCode":"en","text":"AT&T Internet Service"},"formattedAddress":"31 E 17th St, New York, NY 10003, USA","plusCode":{"globalCode":"87G8P2P6+R3","compoundCode":"P2P6+R3 New York, NY, USA"},"adrFormatAddress":"<span class=\"street-address\">31 E 17th St</span>, <span class=\"locality\">New York</span>, <span class=\"region\">NY</span> <span class=\"postal-code\">10003</span>, <span class=\"country-name\">USA</span>","userRatingCount":1,"reviews":[{"name":"places/ChIJSx9YEKJZwokRrgwjhk-RRbM/reviews/ChZDSUhNMG9nS0VJQ0FnSURRaUxlbUN3EAE","rating":5,"authorAttribution":{"photoUri":"https://lh3.googleusercontent.com/a/ACg8ocK7KM8IM5nHuIWaaLCyN7_H8hQ1L33sznfGqB5ySV7s=s128-c0x00000000-cc-rp-mo","uri":"https://www.google.com/maps/contrib/101561345977053017651/reviews","displayName":"Neal Hooks"},"relativePublishTimeDescription":"5 years ago","publishTime":"2018-10-06T20:43:22Z"}],"viewport":{"high":{"latitude":40.73833298029149,"longitude":-73.98846311970848},"low":{"latitude":40.735635019708496,"longitude":-73.9911610802915}},"businessStatus":"OPERATIONAL","shortFormattedAddress":"31 E 17th St, New York"}