{"types":["restaurant","food","point_of_interest","establishment"],"takeout":true,"rating":1,"internationalPhoneNumber":"+1 646-869-0092","iconMaskBaseUri":"https://maps.gstatic.com/mapfiles/place_api/icons/v2/restaurant_pinlet","servesLunch":true,"googleMapsUri":"https://maps.google.com/?cid=6897239683342136906","nationalPhoneNumber":"(646) 869-0092","primaryTypeDisplayName":{"languageCode":"en-US","text":"Restaurant"},"goodForChildren":true,"name":"places/ChIJucVp9gr1wokRSvZV6PLqt18","location":{"latitude":40.85514620000001,"longitude":-73.92974939999999},"iconBackgroundColor":"#FF9E67","addressComponents":[{"types":["street_number"],"languageCode":"en-US","longText":"1601","shortText":"1601"},{"types":["route"],"languageCode":"en","longText":"Saint Nicholas Avenue","shortText":"St Nicholas Ave"},{"types":["sublocality_level_1","sublocality","political"],"languageCode":"en","longText":"Manhattan","shortText":"Manhattan"},{"types":["locality","political"],"languageCode":"en","longText":"New York","shortText":"New York"},{"types":["administrative_area_level_2","political"],"languageCode":"en","longText":"New York County","shortText":"New York County"},{"types":["administrative_area_level_1","political"],"languageCode":"en","longText":"New York","shortText":"NY"},{"types":["country","political"],"languageCode":"en","longText":"United States","shortText":"US"},{"types":["postal_code"],"languageCode":"en-US","longText":"10040","shortText":"10040"},{"types":["postal_code_suffix"],"languageCode":"en-US","longText":"3303","shortText":"3303"}],"id":"ChIJucVp9gr1wokRSvZV6PLqt18","utcOffsetMinutes":-300,"displayName":{"languageCode":"en","text":"Lo Pepe"},"primaryType":"restaurant","formattedAddress":"1601 St Nicholas Ave, New York, NY 10040, USA","plusCode":{"globalCode":"87G8V34C+34","compoundCode":"V34C+34 New York, NY, USA"},"adrFormatAddress":"<span class=\"street-address\">1601 St Nicholas Ave</span>, <span class=\"locality\">New York</span>, <span class=\"region\">NY</span> <span class=\"postal-code\">10040-3303</span>, <span class=\"country-name\">USA</span>","servesDinner":true,"userRatingCount":1,"reviews":[{"name":"places/ChIJucVp9gr1wokRSvZV6PLqt18/reviews/ChZDSUhNMG9nS0VJQ0FnSURaM09fblpREAE","rating":1,"authorAttribution":{"photoUri":"https://lh3.googleusercontent.com/a/ACg8ocIxf-Ddv4SDzCbOjzIkadDl-vl0BxwIEpSYDX6J82nx=s128-c0x00000000-cc-rp-mo","uri":"https://www.google.com/maps/contrib/105606459320125058802/reviews","displayName":"genesis vidal"},"originalText":{"languageCode":"es","text":"Dan muy poca comida por el precio y no se saben comunicar con los clientes"},"relativePublishTimeDescription":"4 months ago","text":{"languageCode":"en-US","text":"They give very little food for the price and they don't know how to communicate with customers"},"publishTime":"2023-09-26T15:47:38Z"}],"dineIn":true,"viewport":{"high":{"latitude":40.85642363029151,"longitude":-73.9284520697085},"low":{"latitude":40.85372566970851,"longitude":-73.93115003029152}},"businessStatus":"OPERATIONAL","shortFormattedAddress":"1601 St Nicholas Ave, New York"}