{"types":["furniture_store","home_improvement_store","home_goods_store","point_of_interest","store","establishment"],"internationalPhoneNumber":"+1 212-794-8807","iconMaskBaseUri":"https://maps.gstatic.com/mapfiles/place_api/icons/v2/shopping_pinlet","googleMapsUri":"https://maps.google.com/?cid=852418206117672097","nationalPhoneNumber":"(212) 794-8807","primaryTypeDisplayName":{"languageCode":"en-US","text":"Furniture Store"},"name":"places/ChIJJ6TKouxYwokRoTS4l9dl1As","location":{"latitude":40.7713831,"longitude":-73.9660373},"iconBackgroundColor":"#4B96F3","addressComponents":[{"types":["street_number"],"languageCode":"en-US","longText":"19","shortText":"19"},{"types":["route"],"languageCode":"en","longText":"East 71st Street","shortText":"E 71st St"},{"types":["sublocality_level_1","sublocality","political"],"languageCode":"en","longText":"Manhattan","shortText":"Manhattan"},{"types":["locality","political"],"languageCode":"en","longText":"New York","shortText":"New York"},{"types":["administrative_area_level_2","political"],"languageCode":"en","longText":"New York County","shortText":"New York County"},{"types":["administrative_area_level_1","political"],"languageCode":"en","longText":"New York","shortText":"NY"},{"types":["country","political"],"languageCode":"en","longText":"United States","shortText":"US"},{"types":["postal_code"],"languageCode":"en-US","longText":"10021","shortText":"10021"},{"types":["postal_code_suffix"],"languageCode":"en-US","longText":"4119","shortText":"4119"}],"id":"ChIJJ6TKouxYwokRoTS4l9dl1As","utcOffsetMinutes":-300,"displayName":{"languageCode":"en","text":"Antique Textiles Gallery Inc"},"primaryType":"furniture_store","formattedAddress":"19 E 71st St, New York, NY 10021, USA","plusCode":{"globalCode":"87G8Q2CM+HH","compoundCode":"Q2CM+HH New York, NY, USA"},"adrFormatAddress":"<span class=\"street-address\">19 E 71st St</span>, <span class=\"locality\">New York</span>, <span class=\"region\">NY</span> <span class=\"postal-code\">10021-4119</span>, <span class=\"country-name\">USA</span>","viewport":{"high":{"latitude":40.7726398802915,"longitude":-73.9647565697085},"low":{"latitude":40.7699419197085,"longitude":-73.9674545302915}},"businessStatus":"CLOSED_TEMPORARILY","shortFormattedAddress":"19 E 71st St, New York"}