{"types":["doctor","health","point_of_interest","establishment"],"internationalPhoneNumber":"+1 212-505-6550","iconMaskBaseUri":"https://maps.gstatic.com/mapfiles/place_api/icons/v2/generic_pinlet","accessibilityOptions":{"wheelchairAccessibleEntrance":true,"wheelchairAccessibleRestroom":true},"googleMapsUri":"https://maps.google.com/?cid=15877725458483231773","nationalPhoneNumber":"(212) 505-6550","primaryTypeDisplayName":{"languageCode":"en-US","text":"Doctor"},"name":"places/ChIJFWtGP55ZwokRHbwRQi4DWdw","location":{"latitude":40.7318514,"longitude":-73.9845835},"iconBackgroundColor":"#7B9EB0","addressComponents":[{"types":["street_number"],"languageCode":"en-US","longText":"310","shortText":"310"},{"types":["route"],"languageCode":"en","longText":"East 14th Street","shortText":"E 14th St"},{"types":["sublocality_level_1","sublocality","political"],"languageCode":"en","longText":"Manhattan","shortText":"Manhattan"},{"types":["locality","political"],"languageCode":"en","longText":"New York","shortText":"New York"},{"types":["administrative_area_level_2","political"],"languageCode":"en","longText":"New York County","shortText":"New York County"},{"types":["administrative_area_level_1","political"],"languageCode":"en","longText":"New York","shortText":"NY"},{"types":["country","political"],"languageCode":"en","longText":"United States","shortText":"US"},{"types":["postal_code"],"languageCode":"en-US","longText":"10003","shortText":"10003"}],"id":"ChIJFWtGP55ZwokRHbwRQi4DWdw","utcOffsetMinutes":-300,"displayName":{"languageCode":"en","text":"Ophthalmic Consultants, P.C."},"primaryType":"doctor","formattedAddress":"310 E 14th St, New York, NY 10003, USA","restroom":true,"plusCode":{"globalCode":"87G8P2J8+P5","compoundCode":"P2J8+P5 New York, NY, USA"},"adrFormatAddress":"<span class=\"street-address\">310 E 14th St</span>, <span class=\"locality\">New York</span>, <span class=\"region\">NY</span> <span class=\"postal-code\">10003</span>, <span class=\"country-name\">USA</span>","viewport":{"high":{"latitude":40.7333331802915,"longitude":-73.98313681970848},"low":{"latitude":40.7306352197085,"longitude":-73.9858347802915}},"businessStatus":"OPERATIONAL","shortFormattedAddress":"310 E 14th St, New York"}