{"types":["consultant","point_of_interest","establishment"],"internationalPhoneNumber":"+1 201-772-3672","iconMaskBaseUri":"https://maps.gstatic.com/mapfiles/place_api/icons/v2/generic_pinlet","googleMapsUri":"https://maps.google.com/?cid=10780018403194174512","nationalPhoneNumber":"(201) 772-3672","primaryTypeDisplayName":{"languageCode":"en-US","text":"Consultant"},"name":"places/ChIJ1csH-HP2wokRMPyPap9RmpU","location":{"latitude":40.8128502,"longitude":-73.9418704},"iconBackgroundColor":"#7B9EB0","addressComponents":[{"types":["route"],"languageCode":"en","longText":"Malcolm X Boulevard","shortText":"Malcolm X Blvd"},{"types":["sublocality_level_1","sublocality","political"],"languageCode":"en","longText":"Manhattan","shortText":"Manhattan"},{"types":["locality","political"],"languageCode":"en","longText":"New York","shortText":"New York"},{"types":["administrative_area_level_2","political"],"languageCode":"en","longText":"New York County","shortText":"New York County"},{"types":["administrative_area_level_1","political"],"languageCode":"en","longText":"New York","shortText":"NY"},{"types":["country","political"],"languageCode":"en","longText":"United States","shortText":"US"},{"types":["postal_code"],"languageCode":"en-US","longText":"10037","shortText":"10037"}],"id":"ChIJ1csH-HP2wokRMPyPap9RmpU","utcOffsetMinutes":-300,"displayName":{"languageCode":"en","text":"SPAD NUGGET"},"primaryType":"consultant","formattedAddress":"133rd &, Malcolm X Blvd, New York, NY 10037, USA","plusCode":{"globalCode":"87G8R375+47","compoundCode":"R375+47 New York, NY, USA"},"adrFormatAddress":"133rd &amp;, <span class=\"street-address\">Malcolm X Blvd</span>, <span class=\"locality\">New York</span>, <span class=\"region\">NY</span> <span class=\"postal-code\">10037</span>, <span class=\"country-name\">USA</span>","viewport":{"high":{"latitude":40.814199180291496,"longitude":-73.94052141970849},"low":{"latitude":40.8115012197085,"longitude":-73.94321938029151}},"businessStatus":"CLOSED_TEMPORARILY","shortFormattedAddress":"133rd &, Malcolm X Blvd, New York"}