{"websiteUri":"http://www.nyu.edu/about/news-publications/news/2002/october/lillian_vernon_center_for.html","types":["point_of_interest","establishment"],"internationalPhoneNumber":"+1 212-998-6848","iconMaskBaseUri":"https://maps.gstatic.com/mapfiles/place_api/icons/v2/school_pinlet","accessibilityOptions":{"wheelchairAccessibleEntrance":true},"googleMapsUri":"https://maps.google.com/?cid=7801369557576808052","nationalPhoneNumber":"(212) 998-6848","name":"places/ChIJq6pO45ZZwokRdHbpeEcIRGw","location":{"latitude":40.7343531,"longitude":-73.997993},"iconBackgroundColor":"#7B9EB0","addressComponents":[{"types":["street_number"],"languageCode":"en-US","longText":"58","shortText":"58"},{"types":["route"],"languageCode":"en","longText":"West 10th Street","shortText":"W 10th St"},{"types":["sublocality_level_1","sublocality","political"],"languageCode":"en","longText":"Manhattan","shortText":"Manhattan"},{"types":["locality","political"],"languageCode":"en","longText":"New York","shortText":"New York"},{"types":["administrative_area_level_2","political"],"languageCode":"en","longText":"New York County","shortText":"New York County"},{"types":["administrative_area_level_1","political"],"languageCode":"en","longText":"New York","shortText":"NY"},{"types":["country","political"],"languageCode":"en","longText":"United States","shortText":"US"},{"types":["postal_code"],"languageCode":"en-US","longText":"10011","shortText":"10011"},{"types":["postal_code_suffix"],"languageCode":"en-US","longText":"8702","shortText":"8702"}],"id":"ChIJq6pO45ZZwokRdHbpeEcIRGw","utcOffsetMinutes":-300,"displayName":{"languageCode":"en","text":"NYU - Lillian Vernon Center for International Affairs"},"formattedAddress":"58 W 10th St, New York, NY 10011, USA","plusCode":{"globalCode":"87G8P2M2+PR","compoundCode":"P2M2+PR New York, NY, USA"},"adrFormatAddress":"<span class=\"street-address\">58 W 10th St</span>, <span class=\"locality\">New York</span>, <span class=\"region\">NY</span> <span class=\"postal-code\">10011-8702</span>, <span class=\"country-name\">USA</span>","viewport":{"high":{"latitude":40.73575683029149,"longitude":-73.99660221970848},"low":{"latitude":40.73305886970849,"longitude":-73.9993001802915}},"businessStatus":"OPERATIONAL","shortFormattedAddress":"58 W 10th St, New York"}