{"websiteUri":"https://www.upperwestsidedermatology.com/dr-falguni-asrani","types":["doctor","health","point_of_interest","establishment"],"rating":4,"internationalPhoneNumber":"+1 212-769-0069","iconMaskBaseUri":"https://maps.gstatic.com/mapfiles/place_api/icons/v2/generic_pinlet","accessibilityOptions":{"wheelchairAccessibleRestroom":true},"googleMapsUri":"https://maps.google.com/?cid=7769418692949895989","nationalPhoneNumber":"(212) 769-0069","primaryTypeDisplayName":{"languageCode":"en-US","text":"Doctor"},"name":"places/ChIJ4WaMGGJYwokRNeuOGCOF0ms","location":{"latitude":40.780429,"longitude":-73.98439359999999},"iconBackgroundColor":"#7B9EB0","addressComponents":[{"types":["subpremise"],"languageCode":"en","longText":"Apt 1B","shortText":"Apt 1B"},{"types":["street_number"],"languageCode":"en-US","longText":"277","shortText":"277"},{"types":["route"],"languageCode":"en","longText":"West End Avenue","shortText":"West End Ave"},{"types":["sublocality_level_1","sublocality","political"],"languageCode":"en","longText":"Manhattan","shortText":"Manhattan"},{"types":["locality","political"],"languageCode":"en","longText":"New York","shortText":"New York"},{"types":["administrative_area_level_2","political"],"languageCode":"en","longText":"New York County","shortText":"New York County"},{"types":["administrative_area_level_1","political"],"languageCode":"en","longText":"New York","shortText":"NY"},{"types":["country","political"],"languageCode":"en","longText":"United States","shortText":"US"},{"types":["postal_code"],"languageCode":"en-US","longText":"10023","shortText":"10023"}],"id":"ChIJ4WaMGGJYwokRNeuOGCOF0ms","utcOffsetMinutes":-300,"displayName":{"languageCode":"en","text":"Falguni Asrani"},"primaryType":"doctor","formattedAddress":"277 West End Ave Apt 1B, New York, NY 10023, USA","restroom":true,"plusCode":{"globalCode":"87G8Q2J8+56","compoundCode":"Q2J8+56 New York, NY, USA"},"adrFormatAddress":"<span class=\"street-address\">277 West End Ave Apt 1B</span>, <span class=\"locality\">New York</span>, <span class=\"region\">NY</span> <span class=\"postal-code\">10023</span>, <span class=\"country-name\">USA</span>","userRatingCount":2,"reviews":[{"name":"places/ChIJ4WaMGGJYwokRNeuOGCOF0ms/reviews/ChZDSUhNMG9nS0VJQ0FnSUQyeE1fSUpnEAE","rating":5,"authorAttribution":{"photoUri":"https://lh3.googleusercontent.com/a-/ALV-UjVaLrzUvhT5emX1vBf9QP7oUBQb8II9BbP_Tq6KYktLXDbM=s128-c0x00000000-cc-rp-mo-ba4","uri":"https://www.google.com/maps/contrib/102812759620271573408/reviews","displayName":"Kevin “Slater” Ryan"},"originalText":{"languageCode":"en","text":"Great Doctor, had been visiting remotely and provided wonderful, compassionate care!"},"relativePublishTimeDescription":"a year ago","text":{"languageCode":"en","text":"Great Doctor, had been visiting remotely and provided wonderful, compassionate care!"},"publishTime":"2022-05-06T17:38:25Z"},{"name":"places/ChIJ4WaMGGJYwokRNeuOGCOF0ms/reviews/ChZDSUhNMG9nS0VJQ0FnSUNXcUluVUZ3EAE","rating":3,"authorAttribution":{"photoUri":"https://lh3.googleusercontent.com/a/ACg8ocKZdglHQxecGsxLv94UrrRoInALCw7iTWVrhgcgI-qr=s128-c0x00000000-cc-rp-mo","uri":"https://www.google.com/maps/contrib/104590318545062591272/reviews","displayName":"Shana Metcalf"},"relativePublishTimeDescription":"a year ago","publishTime":"2022-02-18T15:49:06Z"}],"viewport":{"high":{"latitude":40.781718980291494,"longitude":-73.98290486970849},"low":{"latitude":40.779021019708495,"longitude":-73.9856028302915}},"businessStatus":"OPERATIONAL","shortFormattedAddress":"277 West End Ave Apt 1B, New York"}