{"types":["shopping_mall","point_of_interest","establishment"],"iconMaskBaseUri":"https://maps.gstatic.com/mapfiles/place_api/icons/v2/shopping_pinlet","accessibilityOptions":{"wheelchairAccessibleEntrance":true},"googleMapsUri":"https://maps.google.com/?cid=13952895272390481605","primaryTypeDisplayName":{"languageCode":"en-US","text":"Shopping Mall"},"name":"places/ChIJ1baOIBhZwokRxdYPG1OkosE","location":{"latitude":40.7596749,"longitude":-74.0039517},"iconBackgroundColor":"#4B96F3","addressComponents":[{"types":["street_number"],"languageCode":"en-US","longText":"455","shortText":"455"},{"types":["route"],"languageCode":"en","longText":"12th Avenue","shortText":"12th Ave"},{"types":["sublocality_level_1","sublocality","political"],"languageCode":"en","longText":"Manhattan","shortText":"Manhattan"},{"types":["locality","political"],"languageCode":"en","longText":"New York","shortText":"New York"},{"types":["administrative_area_level_2","political"],"languageCode":"en","longText":"New York County","shortText":"New York County"},{"types":["administrative_area_level_1","political"],"languageCode":"en","longText":"New York","shortText":"NY"},{"types":["country","political"],"languageCode":"en","longText":"United States","shortText":"US"},{"types":["postal_code"],"languageCode":"en-US","longText":"10018","shortText":"10018"}],"id":"ChIJ1baOIBhZwokRxdYPG1OkosE","utcOffsetMinutes":-300,"displayName":{"languageCode":"ko","text":"플랙스크루즈 미드타운 탑승위치"},"primaryType":"shopping_mall","formattedAddress":"455 12th Ave, New York, NY 10018, USA","plusCode":{"globalCode":"87G7QX5W+VC","compoundCode":"QX5W+VC New York, NY, USA"},"adrFormatAddress":"<span class=\"street-address\">455 12th Ave</span>, <span class=\"locality\">New York</span>, <span class=\"region\">NY</span> <span class=\"postal-code\">10018</span>, <span class=\"country-name\">USA</span>","viewport":{"high":{"latitude":40.76102388029149,"longitude":-74.00260271970849},"low":{"latitude":40.75832591970849,"longitude":-74.00530068029151}},"businessStatus":"OPERATIONAL","shortFormattedAddress":"455 12th Ave, New York"}