{"websiteUri":"http://www.dupont.com/","types":["point_of_interest","establishment"],"internationalPhoneNumber":"+1 718-705-5952","iconMaskBaseUri":"https://maps.gstatic.com/mapfiles/place_api/icons/v2/generic_pinlet","googleMapsUri":"https://maps.google.com/?cid=2807807201739112276","nationalPhoneNumber":"(718) 705-5952","name":"places/ChIJUxq2wMhZwokRVH9xCcZV9yY","location":{"latitude":40.754399299999996,"longitude":-73.9708809},"iconBackgroundColor":"#7B9EB0","addressComponents":[{"types":["subpremise"],"languageCode":"und","longText":"#39","shortText":"#39"},{"types":["street_number"],"languageCode":"en-US","longText":"211","shortText":"211"},{"types":["route"],"languageCode":"en","longText":"East 48th Street","shortText":"E 48th St"},{"types":["sublocality_level_1","sublocality","political"],"languageCode":"en","longText":"Manhattan","shortText":"Manhattan"},{"types":["locality","political"],"languageCode":"en","longText":"New York","shortText":"New York"},{"types":["administrative_area_level_2","political"],"languageCode":"en","longText":"New York County","shortText":"New York County"},{"types":["administrative_area_level_1","political"],"languageCode":"en","longText":"New York","shortText":"NY"},{"types":["country","political"],"languageCode":"en","longText":"United States","shortText":"US"},{"types":["postal_code"],"languageCode":"en-US","longText":"10017","shortText":"10017"}],"id":"ChIJUxq2wMhZwokRVH9xCcZV9yY","utcOffsetMinutes":-300,"displayName":{"languageCode":"en","text":"DuPont"},"formattedAddress":"211 E 48th St #39, New York, NY 10017, USA","plusCode":{"globalCode":"87G8Q23H+QJ","compoundCode":"Q23H+QJ New York, NY, USA"},"adrFormatAddress":"<span class=\"street-address\">211 E 48th St #39</span>, <span class=\"locality\">New York</span>, <span class=\"region\">NY</span> <span class=\"postal-code\">10017</span>, <span class=\"country-name\">USA</span>","viewport":{"high":{"latitude":40.755689630291506,"longitude":-73.96957501970849},"low":{"latitude":40.75299166970851,"longitude":-73.97227298029149}},"businessStatus":"OPERATIONAL","shortFormattedAddress":"211 E 48th St #39, New York"}