{"types":["grocery_store","food","store","point_of_interest","establishment"],"rating":5,"internationalPhoneNumber":"+1 646-422-7080","iconMaskBaseUri":"https://maps.gstatic.com/mapfiles/place_api/icons/v2/shoppingcart_pinlet","accessibilityOptions":{"wheelchairAccessibleEntrance":true},"googleMapsUri":"https://maps.google.com/?cid=18252055440032873630","nationalPhoneNumber":"(646) 422-7080","primaryTypeDisplayName":{"languageCode":"en-US","text":"Grocery Store"},"name":"places/ChIJd7TkbhPzwokRnjzlG7hTTP0","location":{"latitude":40.868350799999995,"longitude":-73.9185026},"iconBackgroundColor":"#4B96F3","addressComponents":[{"types":["locality","political"],"languageCode":"en","longText":"New York","shortText":"New York"},{"types":["sublocality_level_1","sublocality","political"],"languageCode":"en","longText":"Manhattan","shortText":"Manhattan"},{"types":["administrative_area_level_2","political"],"languageCode":"en","longText":"New York County","shortText":"New York County"},{"types":["administrative_area_level_1","political"],"languageCode":"en","longText":"New York","shortText":"NY"},{"types":["country","political"],"languageCode":"en","longText":"United States","shortText":"US"},{"types":["postal_code"],"languageCode":"en-US","longText":"10034","shortText":"10034"}],"id":"ChIJd7TkbhPzwokRnjzlG7hTTP0","utcOffsetMinutes":-300,"displayName":{"languageCode":"en","text":"Broadway Plus Organic Deli & Grill"},"primaryType":"grocery_store","formattedAddress":"New York, NY 10034, USA","paymentOptions":{"acceptsCreditCards":true,"acceptsCashOnly":false,"acceptsNfc":true},"regularOpeningHours":{"openNow":true,"periods":[{"open":{"day":0,"hour":10,"minute":0},"close":{"day":0,"hour":17,"minute":0}},{"open":{"day":1,"hour":7,"minute":0},"close":{"day":1,"hour":19,"minute":0}},{"open":{"day":2,"hour":7,"minute":0},"close":{"day":2,"hour":19,"minute":0}},{"open":{"day":3,"hour":7,"minute":0},"close":{"day":3,"hour":19,"minute":0}},{"open":{"day":4,"hour":7,"minute":0},"close":{"day":4,"hour":19,"minute":0}},{"open":{"day":5,"hour":7,"minute":0},"close":{"day":5,"hour":19,"minute":0}},{"open":{"day":6,"hour":7,"minute":0},"close":{"day":6,"hour":19,"minute":0}}],"weekdayDescriptions":["Monday: 7:00 AM – 7:00 PM","Tuesday: 7:00 AM – 7:00 PM","Wednesday: 7:00 AM – 7:00 PM","Thursday: 7:00 AM – 7:00 PM","Friday: 7:00 AM – 7:00 PM","Saturday: 7:00 AM – 7:00 PM","Sunday: 10:00 AM – 5:00 PM"]},"plusCode":{"globalCode":"87G8V39J+8H","compoundCode":"V39J+8H New York, NY, USA"},"adrFormatAddress":"<span class=\"locality\">New York</span>, <span class=\"region\">NY</span> <span class=\"postal-code\">10034</span>, <span class=\"country-name\">USA</span>","userRatingCount":4,"reviews":[{"name":"places/ChIJd7TkbhPzwokRnjzlG7hTTP0/reviews/ChdDSUhNMG9nS0VJQ0FnSURnM18zWTBRRRAB","rating":5,"authorAttribution":{"photoUri":"https://lh3.googleusercontent.com/a/ACg8ocLNkuWfmYHsUt9XeDJykw-C6fOzvEhU5lXrg6CxX-hU=s128-c0x00000000-cc-rp-mo","uri":"https://www.google.com/maps/contrib/112604429917648260126/reviews","displayName":"hamid awandeh"},"originalText":{"languageCode":"en","text":"Has the best food great costumer service always on time!!"},"relativePublishTimeDescription":"5 years ago","text":{"languageCode":"en","text":"Has the best food great costumer service always on time!!"},"publishTime":"2018-06-17T15:49:32Z"},{"name":"places/ChIJd7TkbhPzwokRnjzlG7hTTP0/reviews/ChdDSUhNMG9nS0VJQ0FnSUNBelBxYTVnRRAB","rating":5,"authorAttribution":{"photoUri":"https://lh3.googleusercontent.com/a-/ALV-UjWJiSu7-wczkoPHzlPwU0C4--Pua5IKIS9W1bNaQPOBG8I=s128-c0x00000000-cc-rp-mo-ba3","uri":"https://www.google.com/maps/contrib/117867558526294802338/reviews","displayName":"Brad Baillod"},"originalText":{"languageCode":"en","text":"Very clean place."},"relativePublishTimeDescription":"5 years ago","text":{"languageCode":"en","text":"Very clean place."},"publishTime":"2018-05-30T03:35:38Z"},{"name":"places/ChIJd7TkbhPzwokRnjzlG7hTTP0/reviews/ChZDSUhNMG9nS0VJQ0FnSURZaFpmZ1ZBEAE","rating":5,"authorAttribution":{"photoUri":"https://lh3.googleusercontent.com/a-/ALV-UjWxojudPHF9nVdizl1ZADvHBbwvuhRBYqJ1wHoW2pOlsyY=s128-c0x00000000-cc-rp-mo","uri":"https://www.google.com/maps/contrib/115155324514316955487/reviews","displayName":"Aubrey Nolan"},"relativePublishTimeDescription":"4 years ago","publishTime":"2019-05-15T21:52:31Z"},{"name":"places/ChIJd7TkbhPzwokRnjzlG7hTTP0/reviews/ChZDSUhNMG9nS0VJQ0FnSURHd01tMlB3EAE","rating":5,"authorAttribution":{"photoUri":"https://lh3.googleusercontent.com/a/ACg8ocJkyvlA_a06dKdVZ2Yts3NbYCrAQx51EGrm_TSm2qoZ=s128-c0x00000000-cc-rp-mo","uri":"https://www.google.com/maps/contrib/117185571243889509610/reviews","displayName":"Florin Baliaj"},"relativePublishTimeDescription":"2 years ago","publishTime":"2021-11-15T00:04:50Z"}],"viewport":{"high":{"latitude":40.869724230291496,"longitude":-73.9171130697085},"low":{"latitude":40.8670262697085,"longitude":-73.91981103029151}},"businessStatus":"OPERATIONAL","currentOpeningHours":{"openNow":true,"periods":[{"open":{"day":0,"hour":10,"date":{"day":18,"month":2,"year":2024},"minute":0},"close":{"day":0,"hour":17,"date":{"day":18,"month":2,"year":2024},"minute":0}},{"open":{"day":1,"hour":7,"date":{"day":19,"month":2,"year":2024},"minute":0},"close":{"day":1,"hour":19,"date":{"day":19,"month":2,"year":2024},"minute":0}},{"open":{"day":2,"hour":7,"date":{"day":20,"month":2,"year":2024},"minute":0},"close":{"day":2,"hour":19,"date":{"day":20,"month":2,"year":2024},"minute":0}},{"open":{"day":3,"hour":7,"date":{"day":21,"month":2,"year":2024},"minute":0},"close":{"day":3,"hour":19,"date":{"day":21,"month":2,"year":2024},"minute":0}},{"open":{"day":4,"hour":7,"date":{"day":22,"month":2,"year":2024},"minute":0},"close":{"day":4,"hour":19,"date":{"day":22,"month":2,"year":2024},"minute":0}},{"open":{"day":5,"hour":7,"date":{"day":23,"month":2,"year":2024},"minute":0},"close":{"day":5,"hour":19,"date":{"day":23,"month":2,"year":2024},"minute":0}},{"open":{"day":6,"hour":7,"date":{"day":17,"month":2,"year":2024},"minute":0},"close":{"day":6,"hour":19,"date":{"day":17,"month":2,"year":2024},"minute":0}}],"weekdayDescriptions":["Monday: 7:00 AM – 7:00 PM","Tuesday: 7:00 AM – 7:00 PM","Wednesday: 7:00 AM – 7:00 PM","Thursday: 7:00 AM – 7:00 PM","Friday: 7:00 AM – 7:00 PM","Saturday: 7:00 AM – 7:00 PM","Sunday: 10:00 AM – 5:00 PM"]},"shortFormattedAddress":"New York"}